quairkit/__init__.py
quairkit/circuit.py
quairkit/ansatz/__init__.py
quairkit/ansatz/container.py
quairkit/ansatz/encoding.py
quairkit/ansatz/layer.py
quairkit/ansatz/trotter.py
quairkit/application/__init__.py
quairkit/application/comb/__init__.py
quairkit/application/comb/comb.py
quairkit/application/locc/__init__.py
quairkit/application/locc/locc.py
quairkit/core/__init__.py
quairkit/core/base.py
quairkit/core/hamiltonian.py
quairkit/core/intrinsic.py
quairkit/core/latex.py
quairkit/core/test.py
quairkit/core/operator/__init__.py
quairkit/core/operator/base.py
quairkit/core/operator/transpile.py
quairkit/core/state/__init__.py
quairkit/core/state/state.py
quairkit/core/state/backend/__init__.py
quairkit/core/state/backend/base.py
quairkit/core/state/backend/default.py
quairkit/core/state/backend/operator.py
quairkit/core/state/backend/simulator.py
quairkit/core/utils/__init__.py
quairkit/core/utils/check.py
quairkit/core/utils/linalg.py
quairkit/core/utils/matrix.py
quairkit/core/utils/qinfo.py
quairkit/core/utils/representation.py
quairkit/database/__init__.py
quairkit/database/hamiltonian.py
quairkit/database/matrix.py
quairkit/database/random.py
quairkit/database/representation.py
quairkit/database/set.py
quairkit/database/state.py
quairkit/loss/__init__.py
quairkit/loss/distance.py
quairkit/loss/measure.py
quairkit/operator/__init__.py
quairkit/operator/special.py
quairkit/operator/channel/__init__.py
quairkit/operator/channel/base.py
quairkit/operator/channel/common.py
quairkit/operator/channel/custom.py
quairkit/operator/gate/__init__.py
quairkit/operator/gate/base.py
quairkit/operator/gate/custom.py
quairkit/operator/gate/multi_qubit_gate.py
quairkit/operator/gate/single_qubit_gate.py
quairkit/operator/gate/visual.py
quairkit/qinfo/__init__.py
quairkit/qinfo/check.py
quairkit/qinfo/linalg.py
quairkit/qinfo/qinfo.py
quairkit-0.4.4.dist-info/licenses/LICENSE
quairkit-0.4.4.dist-info/METADATA
quairkit-0.4.4.dist-info/WHEEL
quairkit-0.4.4.dist-info/top_level.txt
quairkit-0.4.4.dist-info/RECORD
