Metadata-Version: 2.4
Name: quairkit
Version: 0.4.4
Summary: QuAIRKit is a Python research toolbox for developing quantum computing, quantum information, and quantum machine learning algorithms.
Author-email: "QuAIR team." <leizhang116.4@gmail.com>
Maintainer-email: "QuAIR team." <leizhang116.4@gmail.com>
License-Expression: Apache-2.0
Project-URL: Homepage, https://www.quair.group
Project-URL: Repository, https://github.com/QuAIR/QuAIRKit
Project-URL: Documentation, https://quairkit.com/QuAIRKit
Keywords: quantum computing,quantum information,quantum machine learning,torch
Classifier: Programming Language :: Python :: 3
Classifier: Operating System :: OS Independent
Requires-Python: <4,>=3.9
License-File: LICENSE
Requires-Dist: torch>=2.4.0
Requires-Dist: scipy
Requires-Dist: ipython
Requires-Dist: matplotlib
Requires-Dist: pdf2image
Requires-Dist: pytest-xdist
Requires-Dist: sphinx>=6.1.3
Requires-Dist: readthedocs-sphinx-search
Requires-Dist: sphinx-rtd-theme>=1.3.0
Dynamic: license-file
